{"name":"As a user I want to get a booking by id","id":"booking;as-a-user-i-want-to-get-a-booking-by-id","testSteps":[{"number":1,"description":"When I trigger GET call with the booking id 12","duration":6903,"startTime":"2023-01-16T23:20:29.498974-03:00[America/Argentina/Mendoza]","result":"SUCCESS","precondition":false,"level":0,"children":[{"number":2,"description":"Make get request: /booking/12","duration":6869,"startTime":"2023-01-16T23:20:29.528062-03:00[America/Argentina/Mendoza]","result":"SUCCESS","precondition":false,"level":1,"children":[{"number":3,"description":"GET https://restful-booker.herokuapp.com/booking/12","duration":0,"startTime":"2023-01-16T23:20:36.397283-03:00[America/Argentina/Mendoza]","result":"SUCCESS","restQuery":{"method":"GET","path":"https://restful-booker.herokuapp.com/booking/12","content":"","contentType":"application/json","requestHeaders":"Authorization\u003dBasic YWRtaW46cGFzc3dvcmQxMjM\u003d\n\t\t\t\tAccept\u003d*/*\n\t\t\t\tContent-Type\u003dapplication/json; charset\u003dUTF-8","requestCookies":"","responseHeaders":"Server: Cowboy\nConnection: keep-alive\nX-Powered-By: Express\nContent-Type: application/json; charset\u003dutf-8\nContent-Length: 178\nEtag: W/\"b2-z+MrJlqQWwS2fI0YIOhvDYnqEIM\"\nDate: Tue, 17 Jan 2023 02:20:36 GMT\nVia: 1.1 vegur","responseCookies":"","responseBody":"{\n    \"firstname\": \"Jane\",\n    \"lastname\": \"Doe\",\n    \"totalprice\": 111,\n    \"depositpaid\": true,\n    \"bookingdates\": {\n        \"checkin\": \"2018-01-01\",\n        \"checkout\": \"2019-01-01\"\n    },\n    \"additionalneeds\": \"Extra pillows please\"\n}","statusCode":200},"precondition":false,"level":2}]}]},{"number":4,"description":"Then I see the status code as 200","duration":6,"startTime":"2023-01-16T23:20:36.403644-03:00[America/Argentina/Mendoza]","result":"SUCCESS","precondition":false,"level":0,"children":[{"number":5,"description":"Assert status code: 200","duration":0,"startTime":"2023-01-16T23:20:36.406662-03:00[America/Argentina/Mendoza]","result":"SUCCESS","precondition":false,"level":1}]}],"userStory":{"id":"booking","storyName":"Booking","path":"ApiRequests.feature","type":"feature"},"featureTag":{"name":"Booking","type":"feature","displayName":"Booking"},"title":"As a user I want to get a booking by id","tags":[{"name":"Booking","type":"feature","displayName":"Booking"}],"startTime":"2023-01-16T23:20:29.492314-03:00[America/Argentina/Mendoza]","duration":6919,"projectKey":"","isManualTestingUpToDate":false,"manual":false,"testSource":"Cucumber","result":"SUCCESS"}